{
  "name": "Gussie Caldwell",
  "age": 36,
  "address": {
    "street": "Hesdi Park",
    "city": "Navwicro",
    "state": "PA",
    "zip": "70290"
  },
  "contact": {
    "phone": "(943) 855-7818",
    "servicePhone": "800131794"
  },
  "birthday": "1985-01-19T01:02:22.787Z",
  "ip": "174.168.165.171",
  "foo": "bar",
  "profile": {
    "about": "Cecula pobupu su sep poud cub fozipci ganjir rahja lif to darwuslu cujwezbi coze jilak ba fen uwed. Rilci domom rufepote net gos jewizo teaca peguur vurripu nupu ca wekwih em ni bi. Iha cagafgo ge itozivcir supbiro ahafu ki iwnuewa hem aswe fihizhem wacdulos.",
    "bio": "Ese vami kabodu sutujlag pa vuz ri cacne dudekabi roazobar laah unjejiw adovudsew wakgizal furum gecnah juk vu. Kakrapi ralis gapoboku beden gaddeb fuiluuz wajtemlah cinapep sovojolu pelofiv hoeju jusfazvef rizuf deprolfob baf sic ed. Nijebi wi edimap divceepu irsak in sepej hi bewluk uh torion tuar so innaep. Padzic guhoszo kek heorpe po buihaepi civhi am wed sa wavleka ca wugez molweso edoabku deuwe vom jicvoter. Fo farab er kedrifruf cic coicaem hazap cedal muztivnoc lo waheh cavap zacu toler ropdi. Vuegeme infi we zaicoaca az riwu nihwog as cuvok wif le zud li."
  },
  "apiKey": "223fec08dbdc34d25547c103c2831b51f72f8bceb9832d7fb876e328e612bbc2",
  "currency": {
    "code": "XDR",
    "name": "International Monetary Fund (IMF) Special Drawing Rights"
  }
}